commentlogger/__init__.py
commentlogger/commentlogger.py
commentlogger/prod.py
commentlogger-1.0.post1.dist-info/licenses/LICENSE
commentlogger-1.0.post1.dist-info/METADATA
commentlogger-1.0.post1.dist-info/WHEEL
commentlogger-1.0.post1.dist-info/top_level.txt
commentlogger-1.0.post1.dist-info/RECORD
