Metadata-Version: 2.4
Name: commentlogger
Version: 1.0.post1
Summary: Turn comments into logs
Author-email: Ashwin Panchapakesan <ashwin.panchapakesan@gmail.com>
License-Expression: MIT
Project-URL: Homepage, https://github.com/inspectorG4dget/commentlogger
Project-URL: Issues, https://github.com/inspectorG4dget/commentlogger/issues
Classifier: Programming Language :: Python :: 3
Classifier: Operating System :: OS Independent
Requires-Python: >=3.7
License-File: LICENSE
Dynamic: license-file
